custom_plugins/__init__.py
custom_plugins/alias_str_wrapper.py
gpp_client/__init__.py
gpp_client/client.py
gpp_client/director.py
gpp_client/exceptions.py
gpp_client/logging_utils.py
gpp_client/rest.py
gpp_client/api/__init__.py
gpp_client/api/_client.py
gpp_client/api/async_base_client.py
gpp_client/api/base_model.py
gpp_client/api/base_operation.py
gpp_client/api/custom_fields.py
gpp_client/api/custom_mutations.py
gpp_client/api/custom_queries.py
gpp_client/api/custom_typing_fields.py
gpp_client/api/enums.py
gpp_client/api/exceptions.py
gpp_client/api/get_goats_observations.py
gpp_client/api/get_goats_programs.py
gpp_client/api/get_scheduler_all_programs_id.py
gpp_client/api/get_scheduler_programs.py
gpp_client/api/input_types.py
gpp_client/cli/__init__.py
gpp_client/cli/cli.py
gpp_client/cli/console.py
gpp_client/cli/output.py
gpp_client/cli/utils.py
gpp_client/cli/commands/__init__.py
gpp_client/cli/commands/attachment.py
gpp_client/cli/commands/call_for_proposals.py
gpp_client/cli/commands/config.py
gpp_client/cli/commands/configuration_request.py
gpp_client/cli/commands/goats.py
gpp_client/cli/commands/group.py
gpp_client/cli/commands/observation.py
gpp_client/cli/commands/program.py
gpp_client/cli/commands/program_note.py
gpp_client/cli/commands/scheduler.py
gpp_client/cli/commands/site_status.py
gpp_client/cli/commands/target.py
gpp_client/cli/commands/workflow_state.py
gpp_client/config/__init__.py
gpp_client/config/config.py
gpp_client/config/defaults.py
gpp_client/config/environment.py
gpp_client/config/models.py
gpp_client/coordinator/__init__.py
gpp_client/coordinator/base.py
gpp_client/credentials/__init__.py
gpp_client/credentials/credential_resolver.py
gpp_client/credentials/env_var_reader.py
gpp_client/directors/__init__.py
gpp_client/directors/base.py
gpp_client/directors/goats/__init__.py
gpp_client/directors/goats/goats.py
gpp_client/directors/goats/coordinators/__init__.py
gpp_client/directors/goats/coordinators/observation.py
gpp_client-26.1.1.dist-info/licenses/LICENSE
gpp_client-26.1.1.dist-info/METADATA
gpp_client-26.1.1.dist-info/WHEEL
gpp_client-26.1.1.dist-info/entry_points.txt
gpp_client-26.1.1.dist-info/top_level.txt
gpp_client-26.1.1.dist-info/RECORD
