Metadata-Version: 2.4
Name: gpp-client
Version: 26.1.1
Summary: Gemini Program Platform client.
Author: NOIRLab
License: Copyright (c) 2025 Association of Universities for Research in Astronomy, Inc. (AURA)
Project-URL: Homepage, https://github.com/gemini-hlsw/gpp-client
Project-URL: Source, https://github.com/gemini-hlsw/gpp-client
Project-URL: Issues, https://github.com/gemini-hlsw/gpp-client/issues
Project-URL: Documentation, https://gpp-client.readthedocs.io/en/latest/
Keywords: gemini,gpp,client,program,platform
Classifier: Development Status :: 3 - Alpha
Classifier: Intended Audience :: Science/Research
Classifier: Operating System :: OS Independent
Classifier: Programming Language :: Python :: 3
Classifier: Programming Language :: Python :: 3.10
Classifier: Programming Language :: Python :: 3.11
Classifier: Programming Language :: Python :: 3.12
Classifier: Programming Language :: Python :: 3.13
Classifier: Topic :: Scientific/Engineering :: Astronomy
Requires-Python: >=3.10.0
License-File: LICENSE
Requires-Dist: aiohttp>=3.13.3
Requires-Dist: beautifulsoup4>=4.11.0
Requires-Dist: graphql-core>=3.2.0
Requires-Dist: httpx>=0.23
Requires-Dist: pydantic>=2.0.0
Requires-Dist: toml>=0.10
Requires-Dist: typer>=0.21.1
Requires-Dist: websockets>=14.2
Dynamic: license-file
